footnotes2.py
mdx_footnotes2-0.3.0.dist-info/LICENSE
mdx_footnotes2-0.3.0.dist-info/METADATA
mdx_footnotes2-0.3.0.dist-info/WHEEL
mdx_footnotes2-0.3.0.dist-info/top_level.txt
mdx_footnotes2-0.3.0.dist-info/RECORD
