Metadata-Version: 2.1
Name: mdx-footnotes2
Version: 0.3.0
Summary: The official Python markdown "footnotes" extension, with additional options.
Home-page: https://github.com/wilhelmer/mdx-footnotes2
Author: Manfred Stienstra, Yuri takhteyev and Waylan limberg
Author-email: waylan.limberg@icloud.com
License: UNKNOWN
Platform: UNKNOWN
Classifier: Development Status :: 4 - Beta
Classifier: Operating System :: OS Independent
Classifier: License :: OSI Approved :: BSD License
Classifier: Intended Audience :: Developers
Classifier: Environment :: Web Environment
Classifier: Programming Language :: Python
Classifier: Topic :: Text Processing :: Filters
Classifier: Topic :: Text Processing :: Markup :: HTML
Requires-Dist: Markdown (>=2.0)
